github/__init__.py
github/github.py
github/static/__init__.py
ppextensions/__init__.py
ppextensions/ppmagics/__init__.py
ppextensions/ppmagics/parameters.py
ppextensions/ppmagics/ppmagics.py
ppextensions/ppsql/__init__.py
ppextensions/ppsql/connection/__init__.py
ppextensions/ppsql/connection/basesql.py
ppextensions/ppsql/connection/csvconnection.py
ppextensions/ppsql/connection/hiveconnection.py
ppextensions/ppsql/connection/prestoconnection.py
ppextensions/ppsql/connection/teradataconnection.py
ppextensions/pputils/__init__.py
ppextensions/pputils/utils/__init__.py
ppextensions/pputils/utils/configuration.py
ppextensions/pputils/utils/constants.py
ppextensions/pputils/utils/exceptions.py
ppextensions/pputils/utils/filesystemreader.py
ppextensions/pputils/utils/log.py
ppextensions/pputils/utils/parameterargs.py
ppextensions/pputils/utils/resultset.py
ppextensions/pputils/utils/tableau.py
ppextensions/pputils/utils/utils.py
ppextensions/pputils/utils/yarnapi.py
ppextensions/pputils/widgets/__init__.py
ppextensions/pputils/widgets/messages.py
ppextensions/pputils/widgets/ppwidgets.py
ppextensions/pputils/widgets/widgets.py
ppextensions/pputils/widgets/widgetsfactory.py
scheduler/__init__.py
scheduler/scheduler.py
scheduler/static/__init__.py
scheduler/template/__init__.py
scheduler/template/dag_template.py
ppextensions-0.0.6.dist-info/LICENSE
ppextensions-0.0.6.dist-info/METADATA
ppextensions-0.0.6.dist-info/WHEEL
ppextensions-0.0.6.dist-info/top_level.txt
ppextensions-0.0.6.dist-info/RECORD
